pagacollect/__ini__.py
pagacollect/paga_collect.py
pagacollect-1.0.5.dist-info/LICENSE.txt
pagacollect-1.0.5.dist-info/METADATA
pagacollect-1.0.5.dist-info/WHEEL
pagacollect-1.0.5.dist-info/top_level.txt
pagacollect-1.0.5.dist-info/RECORD
