Metadata-Version: 2.1
Name: pagacollect
Version: 1.0.5
Summary: A helper class/SDK to enable developers easily integrate Paga Collect API
Home-page: https://github.com/Paga-Developer-Community/paga-collect-python-lib
Author: Zubair Abubakar
Author-email: zubair@zubairabubakar.co
License: MIT
Keywords: payment api,paga,paga collect api
Platform: UNKNOWN
Classifier: Development Status :: 5 - Production/Stable
Classifier: Intended Audience :: Developers
Classifier: Topic :: Software Development :: Build Tools
Classifier: License :: OSI Approved :: MIT License
Classifier: Programming Language :: Python :: 3
Classifier: Programming Language :: Python :: 3.4
Classifier: Programming Language :: Python :: 3.5
Classifier: Programming Language :: Python :: 3.6
Requires-Python: >=3.6
License-File: LICENSE.txt
Requires-Dist: requests
